plover_fancytext/__init__.py
plover_fancytext/character_helpers.py
plover_fancytext/common.py
plover_fancytext/crytyping.py
plover_fancytext/extensionplugin.py
plover_fancytext/figlet.py
plover_fancytext/formatterbase.py
plover_fancytext/retro.py
plover_fancytext/sarcasm.py
plover_fancytext/substitute.py
plover_fancytext/testExtensionPlugin.py
plover_fancytext/testRetro.py
plover_fancytext/testSarcasm.py
plover_fancytext/testZalgo.py
plover_fancytext/uwu.py
plover_fancytext/zalgo.py
plover_fancytext-1.9.0.dist-info/LICENSE
plover_fancytext-1.9.0.dist-info/METADATA
plover_fancytext-1.9.0.dist-info/WHEEL
plover_fancytext-1.9.0.dist-info/entry_points.txt
plover_fancytext-1.9.0.dist-info/top_level.txt
plover_fancytext-1.9.0.dist-info/zip-safe
plover_fancytext-1.9.0.dist-info/RECORD
