Metadata-Version: 2.1
Name: plover-fancytext
Version: 1.9.0
Summary: Silly output formatting plugin for Plover
Home-page: https://github.com/psethwick/plover_fancytext
Author: Seth Rider
Author-email: seth.rider@gmail.com
License: GNU General Public License v3 or later (GPLv3+)
Keywords: plover plover_plugin
Classifier: Development Status :: 4 - Beta
Classifier: Environment :: Plugins
Classifier: Intended Audience :: End Users/Desktop
Classifier: License :: OSI Approved :: GNU General Public License v3 or later (GPLv3+)
Classifier: Operating System :: OS Independent
Classifier: Programming Language :: Python :: 3
License-File: LICENSE
Requires-Dist: plover (>=4.0.0.dev7)
Requires-Dist: pyfiglet (>=0.7)
